Metadata-Version: 1.0
Name: fabric3-anaconda
Version: 0.0.1
Summary: Some additional functions for working with anaconda environments in Fabric3.
Home-page: http://pypi.python.org/pypi/fabric3-anaconda/
Author: Barnaby Gray
Author-email: barnaby@pickle.me.uk
License: UNKNOWN
Platform: UNKNOWN
